{
  "_comment": "Единые фильтры пайплайна querulus.dataset. Редактируйте здесь, не в коде шагов.",

  "victim": {
    "_comment": "Фильтр строк victim parquet (pandas query). T0 — заявление первичного убытка.",
    "refund_forms": [
      "Ремонт",
      "Денежная",
      "Денежная. Отказ от ремонта",
      "Ремонт. Смена СТОА"
    ],
    "loss_date_from": "2022-01-01",
    "loss_date_to": "2025-06-30",
    "loss_processes": [
      "Прямое ОСАГО (с 1 марта 2009)",
      "Традиционное ОСАГО"
    ],
    "risk": "Ущерб имуществу третьих лиц",
    "victim_object_type": "Автотранспорт"
  },

  "loss_object_types_sql": {
    "_comment": "VictimObjectType из oisuu81_t_Losses (нет в victim parquet). loss_processes/risk — из victim.",
    "insurance_type_group": "ОСАГо"
  },

  "claims_sql": {
    "_comment": "Общий WHERE для исков (claims.py legacy, target_3_claims в targets.py). Кассация не фильтруется.",
    "claim_origins": ["ВСК", "Обращение к ФУ"],
    "exclude_claim_items": ["ВСК - 3 лицо"],
    "loss_processes": [
      "Прямое ОСАГО (с 1 марта 2009)",
      "Традиционное ОСАГО"
    ]
  },

  "primary_loss": {
    "_comment": "Строка victim: первичный (min) LossNumber. df_calc_agg — последний (max) LossNumber + max Period.",
    "order_by": "loss_number_asc"
  }
}
